{
  "name": "Moto E7 Plus",
  "codename": "guam",
  "category": "moto-e",
  "android": "Android 10",
  "chip": "Snapdragon 460",
  "img": "https://fdn2.gsmarena.com/vv/pics/motorola/motorola-moto-e7-plus-1.jpg",
  "recoveries": [
    { "name": "TWRP", "version": "3.6.2", "author": "TeamWin", "date": "2023-04-10", "link": "#", "size": "75 MB" }
  ],
  "gcams": [
    { "name": "GCam BSG 8.1", "version": "8.1.101", "author": "BSG", "date": "2023-05-15", "link": "#", "size": "88 MB", "recommended": true }
  ],
  "kernels": []
}
